kodama/__init__.py
kodama/dummy.py
kodama-0.0.2.dist-info/METADATA
kodama-0.0.2.dist-info/WHEEL
kodama-0.0.2.dist-info/licenses/LICENSE
kodama-0.0.2.dist-info/RECORD
