Metadata-Version: 2.1
Name: kodama
Version: 0.0.2
Summary: kodama package
Author: CGTrader
License: This code is provided to you by UAB CGTrader, code 302935696, address - Antakalnio str. 17, Vilnius, Lithuania, the company registered with the Register of Legal Entities of the Republic of Lithuania (CGTrader).
Classifier: License :: OSI Approved :: GNU Lesser General Public License v3 (LGPLv3)
Classifier: Operating System :: OS Independent
Classifier: Programming Language :: Python :: 3
Requires-Python: >=3.7
